{"name":"КриптоПати в России","tagline":"","body":"# КриптоПати в России \r\n\r\n[Gitter](https://gitter.im/CryptoPartyRu/next)   \r\n[FB](https://www.facebook.com/CryptoPartyRussia/)   \r\n[VK](https://vk.com/cryptoparty_next)   \r\n[TheQuestion](http://thequestion.ru/topic/96/kriptografiya)   \r\n\r\n\r\n## Предстоящие мероприятия\r\n\r\n[КриптоПати: SecureDrop] (brusov-17.12.15/README.md)   \r\n17 декабря, 19:00, Москва, Корабль Брюсов   \r\n\r\n## Прошедшие мероприятия\r\n\r\n[КриптоПати им. Аарона Шварца] (dubna-3.12.15/README.md)   \r\n3 декабря 2015, 18:00, Дубна, ул. Блохинцева, д. 13\r\n\r\n","google":"","note":"Don't delete this file! It's used internally to help with page regeneration."}